galaxy/__init__.py
galaxy/py.typed
galaxy/webapps/__init__.py
galaxy/webapps/util.py
galaxy/webapps/base/__init__.py
galaxy/webapps/base/api.py
galaxy/webapps/base/controller.py
galaxy/webapps/base/webapp.py
galaxy/webapps/base/static/erricon.ico
galaxy/webapps/base/static/favicon.ico
galaxy/webapps/base/static/favicon.svg
galaxy/webapps/base/static/formatHelp.html
galaxy/webapps/base/static/incompatible-browser.html
galaxy/webapps/base/static/robots.txt
galaxy/webapps/base/static/user_disabled.html
galaxy/webapps/base/static/welcome.sample.html
galaxy/webapps/base/static/images/delete.gif
galaxy/webapps/base/static/images/delete_tag_icon_gray.png
galaxy/webapps/base/static/images/dw.gif
galaxy/webapps/base/static/images/hatch-fade-023858.gif
galaxy/webapps/base/static/images/history.gif
galaxy/webapps/base/static/images/history_down_arrow.gif
galaxy/webapps/base/static/images/history_up_arrow.gif
galaxy/webapps/base/static/images/icon_error_lrg.gif
galaxy/webapps/base/static/images/icon_error_sml.gif
galaxy/webapps/base/static/images/icon_info_lrg.gif
galaxy/webapps/base/static/images/icon_info_sml.gif
galaxy/webapps/base/static/images/icon_success_lrg.gif
galaxy/webapps/base/static/images/icon_success_sml.gif
galaxy/webapps/base/static/images/icon_warning_lrg.gif
galaxy/webapps/base/static/images/icon_warning_sml.gif
galaxy/webapps/base/static/images/loading_large_white_bg.gif
galaxy/webapps/base/static/images/loading_small_white_bg.gif
galaxy/webapps/base/static/images/openid-16x16.gif
galaxy/webapps/base/static/images/rgWebLogo3_test.jpg
galaxy/webapps/base/static/images/square_empty.gif
galaxy/webapps/base/static/images/square_error.gif
galaxy/webapps/base/static/images/square_ok.gif
galaxy/webapps/base/static/images/square_queued.gif
galaxy/webapps/base/static/images/square_running.gif
galaxy/webapps/base/static/images/star.gif
galaxy/webapps/base/static/images/tool_menu_down_arrow.gif
galaxy/webapps/base/static/images/up.gif
galaxy_web_apps-25.0.3.dist-info/licenses/LICENSE
galaxy_web_apps-25.0.3.dist-info/METADATA
galaxy_web_apps-25.0.3.dist-info/WHEEL
galaxy_web_apps-25.0.3.dist-info/entry_points.txt
galaxy_web_apps-25.0.3.dist-info/top_level.txt
galaxy_web_apps-25.0.3.dist-info/RECORD
