Metadata-Version: 2.4
Name: galaxy-web-apps
Version: 25.0.3
Summary: Galaxy web apps
Home-page: https://github.com/galaxyproject/galaxy
Author: Galaxy Project and Community
Author-email: galaxy-committers@lists.galaxyproject.org
License: AFL
Keywords: Galaxy
Classifier: Development Status :: 5 - Production/Stable
Classifier: Environment :: Console
Classifier: Intended Audience :: Developers
Classifier: License :: OSI Approved :: Academic Free License (AFL)
Classifier: Natural Language :: English
Classifier: Operating System :: POSIX
Classifier: Programming Language :: Python :: 3
Classifier: Programming Language :: Python :: 3.9
Classifier: Programming Language :: Python :: 3.10
Classifier: Programming Language :: Python :: 3.11
Classifier: Programming Language :: Python :: 3.12
Classifier: Programming Language :: Python :: 3.13
Classifier: Topic :: Software Development
Classifier: Topic :: Software Development :: Code Generators
Classifier: Topic :: Software Development :: Testing
Requires-Python: >=3.9
License-File: LICENSE
Requires-Dist: galaxy-app
Requires-Dist: galaxy-data
Requires-Dist: galaxy-job-execution
Requires-Dist: galaxy-tool-util
Requires-Dist: galaxy-util[jstree,template]
Requires-Dist: galaxy-web-framework
Requires-Dist: galaxy-web-stack
Requires-Dist: a2wsgi
Requires-Dist: apispec
Requires-Dist: Babel
Requires-Dist: CT3>=3.3.3
Requires-Dist: fastapi>=0.101.0
Requires-Dist: gunicorn
Requires-Dist: httpx
Requires-Dist: gxformat2
Requires-Dist: Mako
Requires-Dist: MarkupSafe
Requires-Dist: Paste
Requires-Dist: pydantic>=2.7.4
Requires-Dist: PyJWT
Requires-Dist: python-dateutil
Requires-Dist: python-multipart
Requires-Dist: PyYAML
Requires-Dist: requests
Requires-Dist: Routes
Requires-Dist: SQLAlchemy!=2.0.36,<2.1,>=2.0
Requires-Dist: starlette
Requires-Dist: starlette-context
Requires-Dist: tuswsgi
Requires-Dist: typing-extensions
Requires-Dist: uvicorn
Requires-Dist: uvloop>=0.21.0
Requires-Dist: WebOb>=1.8.9
Dynamic: license-file
